dataforge_africa/__init__.py
dataforge_africa/nlp/__init__.py
dataforge_africa/nlp/normalization.py
dataforge_africa-0.1.0.dist-info/licenses/LICENSE
dataforge_africa-0.1.0.dist-info/METADATA
dataforge_africa-0.1.0.dist-info/WHEEL
dataforge_africa-0.1.0.dist-info/top_level.txt
dataforge_africa-0.1.0.dist-info/RECORD
