Metadata-Version: 2.4
Name: dataforge-africa
Version: 0.1.0
Summary: Algorithm-first NLP utilities for African languages
Author-email: Partlet Mpheya Mphateng <info@dataforgeafrica.co.za>
License: MIT
Project-URL: Homepage, https://github.com/DataForgeAfrica/dataforge-africa
Project-URL: Repository, https://github.com/DataForgeAfrica/dataforge-africa
Project-URL: Documentation, https://github.com/DataForgeAfrica/dataforge-africa
Keywords: african languages,nlp,algorithm-first ai,language normalization,digital inclusion
Classifier: Programming Language :: Python :: 3
Classifier: License :: OSI Approved :: MIT License
Classifier: Intended Audience :: Education
Classifier: Intended Audience :: Science/Research
Classifier: Topic :: Scientific/Engineering :: Artificial Intelligence
Requires-Python: >=3.8
License-File: LICENSE
Dynamic: license-file
